{
  "id": "e4f30644-91d9-4141-9ed5-cd88dc0fc7e9",
  "name": "GrandChef API",
  "values": [
    {
      "key": "BASE_URL",
      "value": "http://localhost:3003",
      "description": "",
      "type": "text",
      "enabled": true
    },
    {
      "key": "AUTH_TOKEN",
      "value": "",
      "description": "",
      "type": "text",
      "enabled": true
    },
    {
      "key": "ID_CLIENTE",
      "value": "2",
      "description": "",
      "type": "text",
      "enabled": true
    }
  ],
  "_postman_variable_scope": "environment",
  "_postman_exported_at": "2019-05-03T19:19:04.778Z",
  "_postman_exported_using": "Postman/6.0.10"
}